pyiron_vasp/__init__.py
pyiron_vasp/_version.py
pyiron_vasp/dft/__init__.py
pyiron_vasp/dft/bader.py
pyiron_vasp/dft/volumetric.py
pyiron_vasp/dft/waves/__init__.py
pyiron_vasp/dft/waves/dos.py
pyiron_vasp/dft/waves/electronic.py
pyiron_vasp/vasp/__init__.py
pyiron_vasp/vasp/output.py
pyiron_vasp/vasp/procar.py
pyiron_vasp/vasp/structure.py
pyiron_vasp/vasp/vasprun.py
pyiron_vasp/vasp/volumetric_data.py
pyiron_vasp/vasp/parser/__init__.py
pyiron_vasp/vasp/parser/oszicar.py
pyiron_vasp/vasp/parser/outcar.py
pyiron_vasp/vasp/parser/report.py
pyiron_vasp-0.2.19.dist-info/METADATA
pyiron_vasp-0.2.19.dist-info/WHEEL
pyiron_vasp-0.2.19.dist-info/licenses/LICENSE
pyiron_vasp-0.2.19.dist-info/RECORD
