Metadata-Version: 2.4
Name: pyiron_vasp
Version: 0.2.19
Summary: Parser for the Vienna Ab initio Simulation Package (VASP)
Project-URL: Homepage, https://pyiron.org
Project-URL: Documentation, https://pyiron_vasp.readthedocs.io
Project-URL: Repository, https://github.com/pyiron/pyiron_vasp
Author-email: Jan Janssen <janssen@mpie.de>
License: BSD 3-Clause License
License-File: LICENSE
Keywords: pyiron
Classifier: Development Status :: 5 - Production/Stable
Classifier: Intended Audience :: Science/Research
Classifier: License :: OSI Approved :: BSD License
Classifier: Operating System :: OS Independent
Classifier: Programming Language :: Python :: 3.9
Classifier: Programming Language :: Python :: 3.10
Classifier: Programming Language :: Python :: 3.11
Classifier: Programming Language :: Python :: 3.12
Classifier: Programming Language :: Python :: 3.13
Classifier: Programming Language :: Python :: 3.14
Classifier: Topic :: Scientific/Engineering :: Physics
Requires-Python: <3.15,>=3.9
Requires-Dist: ase<=3.27.0,>=3.23.0
Requires-Dist: defusedxml<=0.7.1,>=0.7.0
Requires-Dist: numpy<=2.4.1,>=1.26.0
Requires-Dist: pandas<=3.0.0,>=2.0.3
Requires-Dist: scipy<=1.17.0,>=1.11.1
Provides-Extra: plot
Requires-Dist: matplotlib==3.10.8; extra == 'plot'
